{
  "agent_id": "requirements",
  "agent_name": "UX & Requirements Agent",
  "run_id": "c654d432-f3d3-407a-bd02-a713818375f2",
  "timestamp": "2026-03-09T20:24:51.577446Z",
  "findings": [
    {
      "id": "requirements-001",
      "agent_id": "requirements",
      "type": "requirement",
      "title": "Dashboard Load Time Optimization",
      "description": "Optimize the dashboard load time to ensure it does not exceed 2 seconds for 95th percentile load times.",
      "impact": "critical",
      "confidence": "validated",
      "assumptions": [
        "The new charting library can be optimized for performance."
      ],
      "evidence": [
        {
          "source_id": "PS-401",
          "source_type": "ticket",
          "excerpt": "Dashboard load time regressed from 1.2s to 4.8s after v3.2 deploy.",
          "url": null
        }
      ],
      "recommendations": [
        "Investigate SVG rendering optimizations in the new charting library."
      ],
      "tags": [
        "performance",
        "dashboard"
      ],
      "metadata": {
        "acceptance_criteria": "GIVEN the dashboard is loaded WHEN the user accesses the dashboard THEN the load time should be <= 2 seconds for 95th percentile.",
        "priority": "P0",
        "complexity": "complex",
        "phase": "V1",
        "epic_id": "epic-performance",
        "epic_title": "Dashboard Performance Optimization",
        "story_id": "story-dashboard-load-time",
        "story_title": "Optimize Dashboard Load Time",
        "dependencies": []
      }
    },
    {
      "id": "requirements-002",
      "agent_id": "requirements",
      "type": "requirement",
      "title": "API Latency Improvement",
      "description": "Reduce API response times to ensure p95 latency does not exceed 200ms.",
      "impact": "critical",
      "confidence": "validated",
      "assumptions": [
        "Database query optimizations can be implemented."
      ],
      "evidence": [
        {
          "source_id": "PS-402",
          "source_type": "ticket",
          "excerpt": "API response times degraded 3x after database migration.",
          "url": null
        }
      ],
      "recommendations": [
        "Analyze and optimize the query planner for time-series aggregation."
      ],
      "tags": [
        "performance",
        "API"
      ],
      "metadata": {
        "acceptance_criteria": "GIVEN an API request is made WHEN the request is processed THEN the p95 latency should be <= 200ms.",
        "priority": "P0",
        "complexity": "complex",
        "phase": "V1",
        "epic_id": "epic-performance",
        "epic_title": "API Performance Optimization",
        "story_id": "story-api-latency",
        "story_title": "Improve API Latency",
        "dependencies": []
      }
    },
    {
      "id": "requirements-003",
      "agent_id": "requirements",
      "type": "requirement",
      "title": "WebSocket Memory Leak Fix",
      "description": "Resolve the memory leak issue in WebSocket connections to prevent server crashes.",
      "impact": "critical",
      "confidence": "validated",
      "assumptions": [
        "The memory leak can be identified and fixed in the WebSocket implementation."
      ],
      "evidence": [
        {
          "source_id": "PS-403",
          "source_type": "ticket",
          "excerpt": "Memory leak in real-time WebSocket connections.",
          "url": null
        }
      ],
      "recommendations": [
        "Conduct heap profiling to identify and fix memory leaks."
      ],
      "tags": [
        "performance",
        "WebSocket"
      ],
      "metadata": {
        "acceptance_criteria": "GIVEN a WebSocket connection is established WHEN the connection is active for 8 hours THEN memory usage should not exceed 2MB per hour.",
        "priority": "P0",
        "complexity": "complex",
        "phase": "V1",
        "epic_id": "epic-performance",
        "epic_title": "WebSocket Performance Optimization",
        "story_id": "story-websocket-memory-leak",
        "story_title": "Fix WebSocket Memory Leak",
        "dependencies": []
      }
    },
    {
      "id": "requirements-004",
      "agent_id": "requirements",
      "type": "requirement",
      "title": "Automated Performance Regression Detection",
      "description": "Implement automated performance regression detection in the CI pipeline to catch regressions before deployment.",
      "impact": "high",
      "confidence": "validated",
      "assumptions": [
        "A benchmark suite can be developed and integrated into the CI pipeline."
      ],
      "evidence": [
        {
          "source_id": "PS-404",
          "source_type": "ticket",
          "excerpt": "Implement performance regression detection in CI pipeline.",
          "url": null
        }
      ],
      "recommendations": [
        "Develop a benchmark suite that runs on every PR."
      ],
      "tags": [
        "CI",
        "performance"
      ],
      "metadata": {
        "acceptance_criteria": "GIVEN a PR is submitted WHEN performance benchmarks are run THEN any regression exceeding 15% in p95 latency should block the merge.",
        "priority": "P1",
        "complexity": "medium",
        "phase": "V1",
        "epic_id": "epic-performance",
        "epic_title": "Performance Regression Detection",
        "story_id": "story-performance-regression-detection",
        "story_title": "Implement Performance Regression Detection",
        "dependencies": []
      }
    },
    {
      "id": "requirements-005",
      "agent_id": "requirements",
      "type": "requirement",
      "title": "Customer Status Page Implementation",
      "description": "Create a public status page to provide customers with real-time performance metrics and historical data.",
      "impact": "medium",
      "confidence": "validated",
      "assumptions": [
        "A status page can be developed and hosted."
      ],
      "evidence": [
        {
          "source_id": "PS-405",
          "source_type": "ticket",
          "excerpt": "Customer-facing status page showing real-time performance metrics.",
          "url": null
        }
      ],
      "recommendations": [
        "Design and implement a public status page."
      ],
      "tags": [
        "customer",
        "transparency"
      ],
      "metadata": {
        "acceptance_criteria": "GIVEN the status page is accessed WHEN it is live THEN it should display real-time p50/p95/p99 latencies, error rates, and uptime.",
        "priority": "P1",
        "complexity": "medium",
        "phase": "V1",
        "epic_id": "epic-transparency",
        "epic_title": "Customer Transparency",
        "story_id": "story-status-page",
        "story_title": "Implement Customer Status Page",
        "dependencies": []
      }
    },
    {
      "id": "requirements-006",
      "agent_id": "requirements",
      "type": "requirement",
      "title": "Performance Monitoring and Alerting",
      "description": "Set up monitoring and alerting for key performance metrics to proactively address issues.",
      "impact": "high",
      "confidence": "directional",
      "assumptions": [
        "Monitoring tools can be integrated with existing systems."
      ],
      "evidence": [
        {
          "source_id": "PS-404",
          "source_type": "ticket",
          "excerpt": "Need for performance regression detection.",
          "url": null
        }
      ],
      "recommendations": [
        "Integrate monitoring tools for real-time performance tracking."
      ],
      "tags": [
        "monitoring",
        "alerting"
      ],
      "metadata": {
        "acceptance_criteria": "GIVEN monitoring is set up WHEN performance metrics exceed defined thresholds THEN alerts should be triggered.",
        "priority": "P2",
        "complexity": "medium",
        "phase": "V2",
        "epic_id": "epic-monitoring",
        "epic_title": "Performance Monitoring",
        "story_id": "story-performance-monitoring",
        "story_title": "Set Up Performance Monitoring and Alerting",
        "dependencies": []
      }
    },
    {
      "id": "requirements-007",
      "agent_id": "requirements",
      "type": "requirement",
      "title": "User Feedback Collection Mechanism",
      "description": "Implement a mechanism to collect user feedback on performance issues and overall satisfaction.",
      "impact": "medium",
      "confidence": "directional",
      "assumptions": [
        "Users will provide feedback if prompted."
      ],
      "evidence": [
        {
          "source_id": "PS-405",
          "source_type": "ticket",
          "excerpt": "Lack of customer visibility during incidents.",
          "url": null
        }
      ],
      "recommendations": [
        "Create a feedback form accessible from the dashboard."
      ],
      "tags": [
        "feedback",
        "customer"
      ],
      "metadata": {
        "acceptance_criteria": "GIVEN the feedback form is accessible WHEN users submit feedback THEN it should be recorded and analyzed.",
        "priority": "P2",
        "complexity": "simple",
        "phase": "V2",
        "epic_id": "epic-feedback",
        "epic_title": "User Feedback Collection",
        "story_id": "story-user-feedback",
        "story_title": "Implement User Feedback Collection Mechanism",
        "dependencies": []
      }
    },
    {
      "id": "requirements-008",
      "agent_id": "requirements",
      "type": "requirement",
      "title": "Documentation for Performance Changes",
      "description": "Create documentation outlining the changes made to improve performance and their impact.",
      "impact": "medium",
      "confidence": "directional",
      "assumptions": [
        "Documentation can be created and maintained."
      ],
      "evidence": [
        {
          "source_id": "PS-401",
          "source_type": "ticket",
          "excerpt": "Dashboard load time regressed from 1.2s to 4.8s.",
          "url": null
        }
      ],
      "recommendations": [
        "Document performance changes and their rationale."
      ],
      "tags": [
        "documentation",
        "performance"
      ],
      "metadata": {
        "acceptance_criteria": "GIVEN performance changes are made WHEN documentation is created THEN it should accurately reflect the changes and their impact.",
        "priority": "P3",
        "complexity": "simple",
        "phase": "V2",
        "epic_id": "epic-documentation",
        "epic_title": "Performance Documentation",
        "story_id": "story-performance-documentation",
        "story_title": "Create Documentation for Performance Changes",
        "dependencies": []
      }
    },
    {
      "id": "requirements-009",
      "agent_id": "requirements",
      "type": "requirement",
      "title": "User Training on New Features",
      "description": "Provide training materials for users to understand new features and performance improvements.",
      "impact": "medium",
      "confidence": "directional",
      "assumptions": [
        "Users will benefit from training on new features."
      ],
      "evidence": [
        {
          "source_id": "PS-405",
          "source_type": "ticket",
          "excerpt": "Build a public status page that shows real-time performance metrics.",
          "url": null
        }
      ],
      "recommendations": [
        "Develop training materials and sessions for users."
      ],
      "tags": [
        "training",
        "user"
      ],
      "metadata": {
        "acceptance_criteria": "GIVEN training materials are created WHEN users access them THEN they should understand the new features and improvements.",
        "priority": "P3",
        "complexity": "simple",
        "phase": "V2",
        "epic_id": "epic-training",
        "epic_title": "User Training",
        "story_id": "story-user-training",
        "story_title": "Provide User Training on New Features",
        "dependencies": []
      }
    },
    {
      "id": "requirements-010",
      "agent_id": "requirements",
      "type": "requirement",
      "title": "Accessibility Compliance Review",
      "description": "Conduct a review of the dashboard and status page for accessibility compliance.",
      "impact": "medium",
      "confidence": "directional",
      "assumptions": [
        "Accessibility standards can be applied to the dashboard and status page."
      ],
      "evidence": [
        {
          "source_id": "DOC-001",
          "source_type": "note",
          "excerpt": "Detected accessibility risk keywords.",
          "url": null
        }
      ],
      "recommendations": [
        "Perform an accessibility audit and implement necessary changes."
      ],
      "tags": [
        "accessibility",
        "compliance"
      ],
      "metadata": {
        "acceptance_criteria": "GIVEN the accessibility review is conducted WHEN changes are made THEN the dashboard and status page should meet WCAG 2.1 AA standards.",
        "priority": "P2",
        "complexity": "medium",
        "phase": "V2",
        "epic_id": "epic-accessibility",
        "epic_title": "Accessibility Compliance",
        "story_id": "story-accessibility-review",
        "story_title": "Conduct Accessibility Compliance Review",
        "dependencies": []
      }
    },
    {
      "id": "requirements-011",
      "agent_id": "requirements",
      "type": "requirement",
      "title": "Performance Metrics Monitoring",
      "description": "Implement monitoring for key performance metrics to track improvements over time.",
      "impact": "medium",
      "confidence": "directional",
      "assumptions": [
        "Monitoring tools can be integrated with existing systems."
      ],
      "evidence": [
        {
          "source_id": "metrics-001",
          "source_type": "metric",
          "excerpt": "North Star metric for PageSpeed is the 95th percentile load time.",
          "url": null
        }
      ],
      "recommendations": [
        "Set up dashboards to visualize performance metrics."
      ],
      "tags": [
        "monitoring",
        "metrics"
      ],
      "metadata": {
        "acceptance_criteria": "GIVEN monitoring is set up WHEN performance metrics are tracked THEN they should be visualized in a dashboard.",
        "priority": "P2",
        "complexity": "medium",
        "phase": "V2",
        "epic_id": "epic-monitoring",
        "epic_title": "Performance Monitoring",
        "story_id": "story-performance-metrics-monitoring",
        "story_title": "Implement Performance Metrics Monitoring",
        "dependencies": []
      }
    }
  ],
  "summary": "The analysis identified critical performance regressions affecting dashboard load times and API latency, necessitating immediate optimization efforts. A structured backlog has been created with prioritized requirements, including performance improvements, automated detection, customer transparency, and user feedback mechanisms. Each requirement is detailed with acceptance criteria and dependencies to ensure effective implementation.",
  "errors": []
}