{
  "agent_id": "customer",
  "agent_name": "Customer Insights Agent",
  "run_id": "efd6af80-2df6-45f2-b0e1-7a66fc9f61ae",
  "timestamp": "2026-03-06T12:37:38.056430Z",
  "findings": [
    {
      "id": "customer-001",
      "agent_id": "customer",
      "type": "insight",
      "title": "Critical Accessibility Gaps for Visually Impaired Users",
      "description": "Visually impaired users are unable to navigate the course catalog and complete enrollment due to a lack of ARIA roles and keyboard support. This significantly impacts their ability to use the platform effectively.",
      "impact": "critical",
      "confidence": "validated",
      "assumptions": [
        "Visually impaired users rely on screen readers for navigation.",
        "Accessibility compliance is essential for educational institutions."
      ],
      "evidence": [
        {
          "source_id": "LP-501",
          "source_type": "ticket",
          "excerpt": "Screen reader cannot navigate course catalog or enrollment flow.",
          "url": null
        },
        {
          "source_id": "LP-504",
          "source_type": "ticket",
          "excerpt": "Quiz forms use custom radio buttons and checkboxes that are invisible to screen readers.",
          "url": null
        },
        {
          "source_id": "DOC-002",
          "source_type": "note",
          "excerpt": "James uses JAWS screen reader and is enrolled in mandatory corporate training through LearnPath.",
          "url": null
        }
      ],
      "recommendations": [
        "Implement ARIA roles and keyboard navigation for all UI components."
      ],
      "tags": [
        "accessibility",
        "a11y",
        "visually impaired"
      ],
      "metadata": {}
    },
    {
      "id": "customer-002",
      "agent_id": "customer",
      "type": "insight",
      "title": "Lack of Video Accessibility Features",
      "description": "The absence of captions, transcripts, and keyboard controls in the video player hinders access for deaf, hard-of-hearing, and motor-impaired users, violating multiple WCAG standards.",
      "impact": "critical",
      "confidence": "validated",
      "assumptions": [
        "Video content is essential for learning.",
        "Accessibility features are required for compliance."
      ],
      "evidence": [
        {
          "source_id": "LP-502",
          "source_type": "ticket",
          "excerpt": "Video player lacks captions, transcripts, and keyboard controls.",
          "url": null
        },
        {
          "source_id": "DOC-002",
          "source_type": "note",
          "excerpt": "James cannot complete his required training courses due to the unusable video player.",
          "url": null
        }
      ],
      "recommendations": [
        "Add captions, transcripts, and keyboard controls to the video player."
      ],
      "tags": [
        "accessibility",
        "video",
        "a11y"
      ],
      "metadata": {}
    },
    {
      "id": "customer-003",
      "agent_id": "customer",
      "type": "insight",
      "title": "Color Contrast Issues Across UI Components",
      "description": "60% of UI components fail to meet WCAG AA contrast ratios, making it difficult for users with visual impairments to read content effectively.",
      "impact": "high",
      "confidence": "validated",
      "assumptions": [
        "Color contrast is crucial for readability.",
        "Accessibility compliance is necessary for user satisfaction."
      ],
      "evidence": [
        {
          "source_id": "LP-503",
          "source_type": "ticket",
          "excerpt": "Accessibility audit found that 60% of text elements fail WCAG AA contrast ratios.",
          "url": null
        }
      ],
      "recommendations": [
        "Revise color schemes to ensure compliance with WCAG AA contrast ratios."
      ],
      "tags": [
        "accessibility",
        "color contrast",
        "a11y"
      ],
      "metadata": {}
    },
    {
      "id": "customer-004",
      "agent_id": "customer",
      "type": "insight",
      "title": "Need for VPAT for Compliance and Procurement",
      "description": "The absence of a Voluntary Product Accessibility Template (VPAT) is a significant barrier for potential clients in government and education sectors, impacting purchasing decisions.",
      "impact": "high",
      "confidence": "validated",
      "assumptions": [
        "A VPAT is essential for compliance with Section 508.",
        "Government and educational institutions require documented accessibility compliance."
      ],
      "evidence": [
        {
          "source_id": "LP-505",
          "source_type": "ticket",
          "excerpt": "Government and education sector prospects require a Voluntary Product Accessibility Template (VPAT).",
          "url": null
        },
        {
          "source_id": "DOC-002",
          "source_type": "note",
          "excerpt": "Emily's agency needs a VPAT before any purchasing decision.",
          "url": null
        }
      ],
      "recommendations": [
        "Conduct a full accessibility audit and create a VPAT."
      ],
      "tags": [
        "compliance",
        "VPAT",
        "accessibility"
      ],
      "metadata": {}
    }
  ],
  "summary": "The analysis reveals critical accessibility gaps in LearnPath that affect visually impaired and motor-disabled users, including navigation issues, lack of video accessibility features, and color contrast failures. Additionally, the absence of a VPAT poses significant compliance risks for potential clients in regulated sectors. Immediate action is required to address these issues to enhance user experience and meet legal requirements.",
  "errors": []
}