{
  "agent_id": "metrics",
  "agent_name": "Metrics & Analytics Agent",
  "run_id": "7540bcf1-5d51-4d44-b953-83d435771b67",
  "timestamp": "2026-03-06T13:11:59.636507Z",
  "findings": [
    {
      "id": "metrics-001",
      "agent_id": "metrics",
      "type": "metric",
      "title": "North Star Metric: User Engagement",
      "description": "The North Star metric for SmartNotify is the Daily Active Users (DAU), which reflects the number of unique users engaging with the notification system daily. This metric is crucial as it directly correlates with user retention and satisfaction.",
      "impact": "critical",
      "confidence": "validated",
      "assumptions": [
        "User engagement is a key driver of product success."
      ],
      "evidence": [
        {
          "source_id": "DOC-003",
          "source_type": "metric",
          "excerpt": "dau: 45000",
          "url": null
        }
      ],
      "recommendations": [
        "Monitor DAU trends weekly to assess user engagement."
      ],
      "tags": [
        "north_star"
      ],
      "metadata": {
        "baseline": 45000,
        "target": 60000,
        "measurement_method": "User login tracking"
      }
    },
    {
      "id": "metrics-002",
      "agent_id": "metrics",
      "type": "metric",
      "title": "Primary KPI: Notification Click-Through Rate (CTR)",
      "description": "The Notification Click-Through Rate (CTR) measures the percentage of notifications that users interact with. This metric indicates the effectiveness of notifications in capturing user attention.",
      "impact": "high",
      "confidence": "validated",
      "assumptions": [
        "Higher CTR indicates better notification relevance."
      ],
      "evidence": [
        {
          "source_id": "DOC-003",
          "source_type": "metric",
          "excerpt": "notification_ctr: 0.12",
          "url": null
        }
      ],
      "recommendations": [
        "Aim to increase CTR by optimizing notification content."
      ],
      "tags": [
        "input_metric"
      ],
      "metadata": {
        "baseline": 0.12,
        "target": 0.15,
        "measurement_method": "Analytics tracking of notification interactions"
      }
    },
    {
      "id": "metrics-003",
      "agent_id": "metrics",
      "type": "metric",
      "title": "Primary KPI: Average Notifications per User",
      "description": "This metric tracks the average number of notifications received by each user. It helps in understanding user exposure to notifications and potential fatigue.",
      "impact": "medium",
      "confidence": "validated",
      "assumptions": [
        "Lower average notifications per user can reduce fatigue."
      ],
      "evidence": [
        {
          "source_id": "DOC-003",
          "source_type": "metric",
          "excerpt": "avg_notifications_per_user: 23",
          "url": null
        }
      ],
      "recommendations": [
        "Consider reducing the average notifications per user to minimize fatigue."
      ],
      "tags": [
        "input_metric"
      ],
      "metadata": {
        "baseline": 23,
        "target": 20,
        "measurement_method": "User notification logs"
      }
    },
    {
      "id": "metrics-004",
      "agent_id": "metrics",
      "type": "metric",
      "title": "Guardrail Metric: Unsubscribe Rate",
      "description": "The Unsubscribe Rate measures the percentage of users who opt-out of notifications. A high unsubscribe rate indicates potential issues with notification relevance or frequency.",
      "impact": "high",
      "confidence": "validated",
      "assumptions": [
        "A lower unsubscribe rate is indicative of user satisfaction."
      ],
      "evidence": [
        {
          "source_id": "DOC-003",
          "source_type": "metric",
          "excerpt": "unsubscribe_rate: 0.08",
          "url": null
        }
      ],
      "recommendations": [
        "Monitor unsubscribe rates closely and investigate spikes."
      ],
      "tags": [
        "guardrail"
      ],
      "metadata": {
        "baseline": 0.08,
        "target": 0.05,
        "measurement_method": "User subscription logs"
      }
    },
    {
      "id": "metrics-005",
      "agent_id": "metrics",
      "type": "metric",
      "title": "Guardrail Metric: 95th Percentile Delivery Latency",
      "description": "This metric tracks the 95th percentile delivery latency of notifications. It is critical to ensure timely delivery of notifications to enhance user experience.",
      "impact": "high",
      "confidence": "validated",
      "assumptions": [
        "Lower latency improves user satisfaction with notifications."
      ],
      "evidence": [
        {
          "source_id": "DOC-003",
          "source_type": "metric",
          "excerpt": "p95_delivery_latency_ms: 340",
          "url": null
        }
      ],
      "recommendations": [
        "Reduce latency to below 200ms as per SLO."
      ],
      "tags": [
        "guardrail"
      ],
      "metadata": {
        "baseline": 340,
        "target": 200,
        "measurement_method": "Performance monitoring tools"
      }
    },
    {
      "id": "metrics-006",
      "agent_id": "metrics",
      "type": "gap",
      "title": "Gap in Measurement of User Preferences",
      "description": "There is a lack of data collection regarding user preferences for notification timing and content. This gap hinders the ability to personalize notifications effectively.",
      "impact": "high",
      "confidence": "directional",
      "assumptions": [
        "Understanding user preferences is essential for improving engagement."
      ],
      "evidence": [
        {
          "source_id": "NOTIFY-103",
          "source_type": "ticket",
          "excerpt": "ML model should learn per-user preferences for delivery timing and grouping thresholds.",
          "url": null
        }
      ],
      "recommendations": [
        "Implement user preference surveys and tracking mechanisms."
      ],
      "tags": [
        "gap"
      ],
      "metadata": {}
    },
    {
      "id": "metrics-007",
      "agent_id": "metrics",
      "type": "recommendation",
      "title": "Experiment Opportunity: Notification Timing Optimization",
      "description": "Conduct an experiment to test the impact of different notification timings on user engagement and CTR. This will help identify optimal delivery windows.",
      "impact": "medium",
      "confidence": "directional",
      "assumptions": [
        "Notification timing significantly affects user engagement."
      ],
      "evidence": [
        {
          "source_id": "NOTIFY-103",
          "source_type": "ticket",
          "excerpt": "Batch low-priority notifications into a digest delivered at optimal times.",
          "url": null
        }
      ],
      "recommendations": [
        "Run A/B tests with varied notification timings."
      ],
      "tags": [
        "experiment"
      ],
      "metadata": {
        "statistical_parameters": {
          "sample_size": 1000,
          "confidence_level": 0.95,
          "power": 0.8
        }
      }
    }
  ],
  "summary": "The analysis identifies the North Star metric as Daily Active Users, with supporting KPIs including Notification CTR and Average Notifications per User. Guardrail metrics focus on Unsubscribe Rate and Delivery Latency. A significant measurement gap exists in user preference data, and an experiment opportunity is proposed to optimize notification timing.",
  "errors": []
}