{
  "agent_id": "requirements",
  "agent_name": "UX & Requirements Agent",
  "run_id": "93af80d5-aef9-45f6-9f66-7071944aafa8",
  "timestamp": "2026-03-09T19:59:08.768568Z",
  "findings": [
    {
      "id": "requirements-001",
      "agent_id": "requirements",
      "type": "requirement",
      "title": "Build User Behavior Tracking Pipeline",
      "description": "Implement a data ingestion pipeline that captures browsing history, click patterns, scroll depth, and time-on-page metrics for each authenticated user. The pipeline must handle at minimum 50k events/second at peak.",
      "impact": "high",
      "confidence": "validated",
      "assumptions": [
        "The infrastructure can support the required event throughput."
      ],
      "evidence": [
        {
          "source_id": "PROF-101",
          "source_type": "ticket",
          "excerpt": "Build user behavior tracking pipeline",
          "url": null
        }
      ],
      "recommendations": [
        "Ensure compliance with GDPR during data collection."
      ],
      "tags": [
        "data tracking",
        "GDPR compliance"
      ],
      "metadata": {
        "acceptance_criteria": "GIVEN the user is authenticated, WHEN they browse content, THEN their browsing history and click patterns are captured and streamed to the data lake in real-time.",
        "priority": "P1",
        "complexity": "complex",
        "phase": "MVP",
        "epic_id": "epic-data-tracking",
        "epic_title": "User Behavior Tracking",
        "story_id": "story-user-behavior-pipeline",
        "story_title": "User Behavior Tracking Pipeline",
        "dependencies": []
      }
    },
    {
      "id": "requirements-002",
      "agent_id": "requirements",
      "type": "requirement",
      "title": "Implement ML Recommendation Engine",
      "description": "Build a recommendation engine that uses accumulated user profile data to serve personalized content suggestions, targeting a 20% improvement in content CTR within 60 days.",
      "impact": "high",
      "confidence": "validated",
      "assumptions": [
        "The recommendation algorithms will effectively utilize user data."
      ],
      "evidence": [
        {
          "source_id": "PROF-102",
          "source_type": "ticket",
          "excerpt": "Implement ML recommendation engine",
          "url": null
        }
      ],
      "recommendations": [
        "Conduct A/B testing to optimize the recommendation engine."
      ],
      "tags": [
        "recommendation engine",
        "ML"
      ],
      "metadata": {
        "acceptance_criteria": "GIVEN user profiles are available, WHEN the recommendation engine processes the data, THEN it generates personalized content suggestions with a target CTR improvement of 20%.",
        "priority": "P1",
        "complexity": "complex",
        "phase": "MVP",
        "epic_id": "epic-recommendation-engine",
        "epic_title": "Recommendation Engine",
        "story_id": "story-ml-recommendation-engine",
        "story_title": "ML Recommendation Engine",
        "dependencies": [
          "story-user-behavior-pipeline"
        ]
      }
    },
    {
      "id": "requirements-003",
      "agent_id": "requirements",
      "type": "requirement",
      "title": "Create User Preference Dashboard",
      "description": "Build a user-facing dashboard that displays collected behavioral data, allowing users to see their inferred interests and opt out of specific tracking categories.",
      "impact": "medium",
      "confidence": "directional",
      "assumptions": [
        "Users will engage with the dashboard to manage their preferences."
      ],
      "evidence": [
        {
          "source_id": "PROF-103",
          "source_type": "ticket",
          "excerpt": "Create user preference dashboard",
          "url": null
        }
      ],
      "recommendations": [
        "Ensure the dashboard is user-friendly and accessible."
      ],
      "tags": [
        "user interface",
        "transparency"
      ],
      "metadata": {
        "acceptance_criteria": "GIVEN the user accesses the dashboard, WHEN they view their data, THEN they can see their inferred interests and have options to opt out of specific tracking categories.",
        "priority": "P2",
        "complexity": "medium",
        "phase": "V1",
        "epic_id": "epic-transparency",
        "epic_title": "User Transparency",
        "story_id": "story-user-preference-dashboard",
        "story_title": "User Preference Dashboard",
        "dependencies": [
          "story-user-behavior-pipeline"
        ]
      }
    },
    {
      "id": "requirements-004",
      "agent_id": "requirements",
      "type": "requirement",
      "title": "Add Cross-Device Tracking",
      "description": "Implement cross-device tracking to link user activity across mobile and web sessions, ensuring a unified user profile.",
      "impact": "medium",
      "confidence": "validated",
      "assumptions": [
        "Users will be logged in across devices."
      ],
      "evidence": [
        {
          "source_id": "PROF-104",
          "source_type": "ticket",
          "excerpt": "Add cross-device tracking",
          "url": null
        }
      ],
      "recommendations": [
        "Ensure compliance with privacy regulations."
      ],
      "tags": [
        "cross-device",
        "user profile"
      ],
      "metadata": {
        "acceptance_criteria": "GIVEN a user is logged in on multiple devices, WHEN they interact with content, THEN their activity is linked to their unified profile.",
        "priority": "P1",
        "complexity": "medium",
        "phase": "V1",
        "epic_id": "epic-user-profiling",
        "epic_title": "User Profiling",
        "story_id": "story-cross-device-tracking",
        "story_title": "Cross-Device Tracking",
        "dependencies": [
          "story-user-behavior-pipeline"
        ]
      }
    },
    {
      "id": "requirements-005",
      "agent_id": "requirements",
      "type": "requirement",
      "title": "Implement Data Export for Advertisers",
      "description": "Create an API and batch export system for sharing anonymized user profile segments with advertising partners, ensuring anonymization to prevent re-identification.",
      "impact": "high",
      "confidence": "validated",
      "assumptions": [
        "Advertisers will require cohort-level data."
      ],
      "evidence": [
        {
          "source_id": "PROF-105",
          "source_type": "ticket",
          "excerpt": "Implement data export for advertisers",
          "url": null
        }
      ],
      "recommendations": [
        "Validate the anonymization pipeline to prevent re-identification."
      ],
      "tags": [
        "data export",
        "advertising"
      ],
      "metadata": {
        "acceptance_criteria": "GIVEN the data export system is implemented, WHEN advertisers request user segments, THEN they receive anonymized cohort-level data without individual identifiers.",
        "priority": "P1",
        "complexity": "complex",
        "phase": "V1",
        "epic_id": "epic-data-sharing",
        "epic_title": "Data Sharing with Advertisers",
        "story_id": "story-data-export-advertisers",
        "story_title": "Data Export for Advertisers",
        "dependencies": []
      }
    },
    {
      "id": "requirements-006",
      "agent_id": "requirements",
      "type": "requirement",
      "title": "Conduct GDPR Compliance Audit",
      "description": "Perform a full GDPR compliance audit to address concerns regarding lawful basis for processing, consent mechanisms, and data retention policies.",
      "impact": "critical",
      "confidence": "validated",
      "assumptions": [
        "Legal requirements will be met to launch in the EU market."
      ],
      "evidence": [
        {
          "source_id": "PROF-106",
          "source_type": "ticket",
          "excerpt": "GDPR compliance audit request",
          "url": null
        }
      ],
      "recommendations": [
        "Complete the audit before product launch."
      ],
      "tags": [
        "compliance",
        "GDPR"
      ],
      "metadata": {
        "acceptance_criteria": "GIVEN the audit team is assembled, WHEN the audit is conducted, THEN all GDPR compliance concerns are addressed and documented.",
        "priority": "P0",
        "complexity": "complex",
        "phase": "MVP",
        "epic_id": "epic-compliance",
        "epic_title": "GDPR Compliance",
        "story_id": "story-gdpr-compliance-audit",
        "story_title": "GDPR Compliance Audit",
        "dependencies": []
      }
    },
    {
      "id": "requirements-007",
      "agent_id": "requirements",
      "type": "requirement",
      "title": "User Feedback Collection Mechanism",
      "description": "Implement a mechanism for collecting user feedback on content recommendations and transparency features to continuously improve user experience.",
      "impact": "medium",
      "confidence": "directional",
      "assumptions": [
        "Users will provide feedback on their experience."
      ],
      "evidence": [
        {
          "source_id": "PROF-103",
          "source_type": "ticket",
          "excerpt": "Create user preference dashboard",
          "url": null
        }
      ],
      "recommendations": [
        "Incorporate feedback into product iterations."
      ],
      "tags": [
        "user feedback",
        "improvement"
      ],
      "metadata": {
        "acceptance_criteria": "GIVEN the feedback mechanism is in place, WHEN users provide feedback, THEN it is collected and analyzed for future improvements.",
        "priority": "P2",
        "complexity": "medium",
        "phase": "V1",
        "epic_id": "epic-feedback",
        "epic_title": "User Feedback",
        "story_id": "story-user-feedback-collection",
        "story_title": "User Feedback Collection Mechanism",
        "dependencies": []
      }
    },
    {
      "id": "requirements-008",
      "agent_id": "requirements",
      "type": "requirement",
      "title": "Monitor Privacy Opt-Out Rate",
      "description": "Implement monitoring for the Privacy Opt-Out Rate to ensure compliance with user preferences and privacy regulations.",
      "impact": "high",
      "confidence": "validated",
      "assumptions": [
        "Monitoring tools will be effective in tracking opt-out rates."
      ],
      "evidence": [
        {
          "source_id": "metrics-003",
          "source_type": "metric",
          "excerpt": "Guardrail Metric: Privacy Opt-Out Rate",
          "url": null
        }
      ],
      "recommendations": [
        "Adjust data collection practices based on opt-out trends."
      ],
      "tags": [
        "privacy",
        "monitoring"
      ],
      "metadata": {
        "acceptance_criteria": "GIVEN the monitoring system is in place, WHEN users opt out, THEN the opt-out rate is tracked and reported regularly.",
        "priority": "P1",
        "complexity": "medium",
        "phase": "V1",
        "epic_id": "epic-monitoring",
        "epic_title": "Monitoring User Privacy",
        "story_id": "story-monitor-privacy-opt-out-rate",
        "story_title": "Monitor Privacy Opt-Out Rate",
        "dependencies": []
      }
    },
    {
      "id": "requirements-009",
      "agent_id": "requirements",
      "type": "requirement",
      "title": "A/B Testing for Recommendation Engine",
      "description": "Conduct A/B testing to evaluate the effectiveness of different recommendation algorithms on CTR.",
      "impact": "medium",
      "confidence": "directional",
      "assumptions": [
        "Different algorithms will yield varying results."
      ],
      "evidence": [
        {
          "source_id": "metrics-005",
          "source_type": "doc",
          "excerpt": "Conduct A/B testing to evaluate the effectiveness of different recommendation algorithms",
          "url": null
        }
      ],
      "recommendations": [
        "Analyze results to identify the best-performing model."
      ],
      "tags": [
        "A/B testing",
        "recommendation"
      ],
      "metadata": {
        "acceptance_criteria": "GIVEN the A/B testing framework is set up, WHEN tests are conducted, THEN the results are analyzed to determine the best-performing recommendation algorithm.",
        "priority": "P2",
        "complexity": "medium",
        "phase": "V1",
        "epic_id": "epic-testing",
        "epic_title": "Testing Recommendation Engine",
        "story_id": "story-ab-testing-recommendation-engine",
        "story_title": "A/B Testing for Recommendation Engine",
        "dependencies": [
          "story-ml-recommendation-engine"
        ]
      }
    },
    {
      "id": "requirements-010",
      "agent_id": "requirements",
      "type": "requirement",
      "title": "Implement User Data Export Feature",
      "description": "Allow users to export their data in compliance with GDPR, enabling them to access their personal information.",
      "impact": "high",
      "confidence": "validated",
      "assumptions": [
        "Users will want to access their data."
      ],
      "evidence": [
        {
          "source_id": "PROF-106",
          "source_type": "ticket",
          "excerpt": "GDPR compliance audit request",
          "url": null
        }
      ],
      "recommendations": [
        "Ensure the export feature is user-friendly."
      ],
      "tags": [
        "data export",
        "GDPR"
      ],
      "metadata": {
        "acceptance_criteria": "GIVEN the user requests their data export, WHEN the request is processed, THEN the user receives their personal data in a structured format.",
        "priority": "P0",
        "complexity": "medium",
        "phase": "V2",
        "epic_id": "epic-compliance",
        "epic_title": "GDPR Compliance",
        "story_id": "story-user-data-export",
        "story_title": "User Data Export Feature",
        "dependencies": []
      }
    },
    {
      "id": "requirements-011",
      "agent_id": "requirements",
      "type": "requirement",
      "title": "Implement User Consent Management",
      "description": "Create a system for managing user consent for data collection and processing, ensuring compliance with GDPR requirements.",
      "impact": "critical",
      "confidence": "validated",
      "assumptions": [
        "Users will need to provide consent for data processing."
      ],
      "evidence": [
        {
          "source_id": "PROF-106",
          "source_type": "ticket",
          "excerpt": "GDPR compliance audit request",
          "url": null
        }
      ],
      "recommendations": [
        "Ensure the consent management system is transparent and user-friendly."
      ],
      "tags": [
        "consent",
        "GDPR"
      ],
      "metadata": {
        "acceptance_criteria": "GIVEN the consent management system is implemented, WHEN users interact with the platform, THEN they are prompted to provide consent for data collection and processing.",
        "priority": "P0",
        "complexity": "complex",
        "phase": "MVP",
        "epic_id": "epic-compliance",
        "epic_title": "GDPR Compliance",
        "story_id": "story-user-consent-management",
        "story_title": "User Consent Management",
        "dependencies": []
      }
    },
    {
      "id": "requirements-012",
      "agent_id": "requirements",
      "type": "requirement",
      "title": "Implement Data Retention Policies",
      "description": "Establish data retention policies that comply with GDPR, ensuring that user data is retained only as long as necessary.",
      "impact": "critical",
      "confidence": "validated",
      "assumptions": [
        "Data retention policies will be enforced."
      ],
      "evidence": [
        {
          "source_id": "PROF-106",
          "source_type": "ticket",
          "excerpt": "GDPR compliance audit request",
          "url": null
        }
      ],
      "recommendations": [
        "Regularly review and update data retention policies."
      ],
      "tags": [
        "data retention",
        "GDPR"
      ],
      "metadata": {
        "acceptance_criteria": "GIVEN the data retention policies are established, WHEN user data is processed, THEN it is retained only for the duration necessary for its purpose.",
        "priority": "P0",
        "complexity": "complex",
        "phase": "MVP",
        "epic_id": "epic-compliance",
        "epic_title": "GDPR Compliance",
        "story_id": "story-data-retention-policies",
        "story_title": "Data Retention Policies",
        "dependencies": []
      }
    }
  ],
  "summary": "The analysis resulted in a comprehensive set of requirements focused on user behavior tracking, GDPR compliance, and user transparency. Each requirement is structured with clear acceptance criteria, priorities, and dependencies, ensuring a well-defined product backlog for the PersonaLens User Profiling project.",
  "errors": []
}